XStatic_Angular_Notify-2.5.1.0-py2.7-nspkg.pth
XStatic_Angular_Notify-2.5.1.0.dist-info/METADATA
XStatic_Angular_Notify-2.5.1.0.dist-info/RECORD
XStatic_Angular_Notify-2.5.1.0.dist-info/WHEEL
XStatic_Angular_Notify-2.5.1.0.dist-info/namespace_packages.txt
XStatic_Angular_Notify-2.5.1.0.dist-info/top_level.txt
xstatic/pkg/angular_notify/__init__.py
xstatic/pkg/angular_notify/data/angular-notify.css
xstatic/pkg/angular_notify/data/angular-notify.html
xstatic/pkg/angular_notify/data/angular-notify.js
