Metadata-Version: 2.1
Name: XStatic-Angular-Notify
Version: 2.5.1.0
Summary: Angular-Notify 2.5.1 (XStatic packaging standard)
Home-page: https://github.com/cgross/angular-notify
Maintainer: xinni.ge
Maintainer-email: xinni.ge@ntt.com
License: MIT
Keywords: angular_notify xstatic
Platform: any
